pytimings/__init__.py
pytimings/_version.py
pytimings/cli.py
pytimings/processing.py
pytimings/timer.py
pytimings/tools.py
pytimings/plotting/__init__.py
pytimings/plotting/colors.py
pytimings-2025.1.0.dist-info/licenses/AUTHORS.md
pytimings-2025.1.0.dist-info/licenses/LICENSE
pytimings-2025.1.0.dist-info/METADATA
pytimings-2025.1.0.dist-info/WHEEL
pytimings-2025.1.0.dist-info/entry_points.txt
pytimings-2025.1.0.dist-info/top_level.txt
pytimings-2025.1.0.dist-info/RECORD
