Metadata-Version: 2.4
Name: pytimings
Version: 2025.1.0
Summary: MPI Aware section timings
Home-page: https://github.com/renefritze/pytimings
Author: René Fritze
Author-email: coding@fritze.me
License: BSD license
Keywords: pytimings
Classifier: Development Status :: 2 - Pre-Alpha
Classifier: Intended Audience :: Developers
Classifier: License :: OSI Approved :: BSD License
Classifier: Natural Language :: English
Classifier: Programming Language :: Python :: 3
Classifier: Programming Language :: Python :: 3.7
Classifier: Programming Language :: Python :: 3.8
Classifier: Programming Language :: Python :: 3.9
Classifier: Programming Language :: Python :: 3.10
Requires-Python: >=3.7
License-File: LICENSE
License-File: AUTHORS.md
Requires-Dist: packaging
Requires-Dist: typer
Requires-Dist: rich
Requires-Dist: pandas
Requires-Dist: matplotlib
Requires-Dist: jupytext
Requires-Dist: psutil
Requires-Dist: setuptools
Requires-Dist: wheel
Requires-Dist: pytest-runner>=2.9
Requires-Dist: packaging
Provides-Extra: ci
Requires-Dist: pytest; extra == "ci"
Requires-Dist: pytest-cov; extra == "ci"
Requires-Dist: pytest-xdist; extra == "ci"
Requires-Dist: check-manifest; extra == "ci"
Requires-Dist: ruff; extra == "ci"
Requires-Dist: pre-commit; extra == "ci"
Requires-Dist: pytest-pycharm; extra == "ci"
Requires-Dist: readme_renderer[md]; extra == "ci"
Requires-Dist: rstcheck; extra == "ci"
Requires-Dist: codecov; extra == "ci"
Requires-Dist: twine; extra == "ci"
Requires-Dist: pytest-memprof; extra == "ci"
Requires-Dist: pytest-regressions; extra == "ci"
Requires-Dist: pytest-datadir; extra == "ci"
Requires-Dist: pytest-timeout; extra == "ci"
Requires-Dist: docutils; extra == "ci"
Requires-Dist: numpy; extra == "ci"
Provides-Extra: docs
Requires-Dist: sphinx; extra == "docs"
Requires-Dist: matplotlib; extra == "docs"
Requires-Dist: python-slugify; extra == "docs"
Requires-Dist: myst-nb>=0.14.0; extra == "docs"
Requires-Dist: sphinx-autoapi>=1.8; extra == "docs"
Requires-Dist: packaging; extra == "docs"
Requires-Dist: typer; extra == "docs"
Requires-Dist: rich; extra == "docs"
Requires-Dist: pandas; extra == "docs"
Requires-Dist: matplotlib; extra == "docs"
Requires-Dist: jupytext; extra == "docs"
Requires-Dist: psutil; extra == "docs"
Requires-Dist: setuptools; extra == "docs"
Requires-Dist: wheel; extra == "docs"
Requires-Dist: pytest-runner>=2.9; extra == "docs"
Requires-Dist: packaging; extra == "docs"
Provides-Extra: full
Requires-Dist: mpi4py; extra == "full"
Requires-Dist: pytest; extra == "full"
Requires-Dist: pytest-cov; extra == "full"
Requires-Dist: pytest-xdist; extra == "full"
Requires-Dist: check-manifest; extra == "full"
Requires-Dist: ruff; extra == "full"
Requires-Dist: pre-commit; extra == "full"
Requires-Dist: pytest-pycharm; extra == "full"
Requires-Dist: readme_renderer[md]; extra == "full"
Requires-Dist: rstcheck; extra == "full"
Requires-Dist: codecov; extra == "full"
Requires-Dist: twine; extra == "full"
Requires-Dist: pytest-memprof; extra == "full"
Requires-Dist: pytest-regressions; extra == "full"
Requires-Dist: pytest-datadir; extra == "full"
Requires-Dist: pytest-timeout; extra == "full"
Requires-Dist: docutils; extra == "full"
Requires-Dist: numpy; extra == "full"
Requires-Dist: sphinx; extra == "full"
Requires-Dist: matplotlib; extra == "full"
Requires-Dist: python-slugify; extra == "full"
Requires-Dist: myst-nb>=0.14.0; extra == "full"
Requires-Dist: sphinx-autoapi>=1.8; extra == "full"
Requires-Dist: packaging; extra == "full"
Requires-Dist: typer; extra == "full"
Requires-Dist: rich; extra == "full"
Requires-Dist: pandas; extra == "full"
Requires-Dist: matplotlib; extra == "full"
Requires-Dist: jupytext; extra == "full"
Requires-Dist: psutil; extra == "full"
Requires-Dist: setuptools; extra == "full"
Requires-Dist: wheel; extra == "full"
Requires-Dist: pytest-runner>=2.9; extra == "full"
Requires-Dist: packaging; extra == "full"
Dynamic: author
Dynamic: author-email
Dynamic: classifier
Dynamic: description
Dynamic: description-content-type
Dynamic: home-page
Dynamic: keywords
Dynamic: license
Dynamic: license-file
Dynamic: provides-extra
Dynamic: requires-dist
Dynamic: requires-python
Dynamic: summary
